customattack/__init__.py
customattack/__main__.py
customattack/attack.py
customattack/attack_args.py
customattack/attacker.py
customattack/dataset_args.py
customattack/fetchCIFAR10.py
customattack/model_args.py
customattack/trainer.py
customattack/trainer_visual.py
customattack/training_args.py
customattack/attack_results/__init__.py
customattack/attack_results/attack_result.py
customattack/attack_results/failed_attack_result.py
customattack/attack_results/maximized_attack_result.py
customattack/attack_results/skipped_attack_result.py
customattack/attack_results/successful_attack_result.py
customattack/commands/__init__.py
customattack/commands/attack_command.py
customattack/commands/customattack_cli.py
customattack/commands/customattack_command.py
customattack/commands/train_model_command.py
customattack/constraints/__init__.py
customattack/constraints/constraint.py
customattack/constraints/pre_transformation_constraint.py
customattack/constraints/grammaticality/__init__.py
customattack/constraints/grammaticality/cola.py
customattack/constraints/grammaticality/language_tool.py
customattack/constraints/grammaticality/part_of_speech.py
customattack/constraints/grammaticality/language_models/__init__.py
customattack/constraints/grammaticality/language_models/gpt2.py
customattack/constraints/grammaticality/language_models/language_model_constraint.py
customattack/constraints/grammaticality/language_models/google_language_model/__init__.py
customattack/constraints/grammaticality/language_models/google_language_model/alzantot_goog_lm.py
customattack/constraints/grammaticality/language_models/google_language_model/google_language_model.py
customattack/constraints/grammaticality/language_models/google_language_model/lm_data_utils.py
customattack/constraints/grammaticality/language_models/google_language_model/lm_utils.py
customattack/constraints/grammaticality/language_models/learning_to_write/__init__.py
customattack-1.4.dist-info/METADATA
customattack-1.4.dist-info/WHEEL
customattack-1.4.dist-info/entry_points.txt
customattack-1.4.dist-info/top_level.txt
customattack-1.4.dist-info/RECORD
