Metadata-Version: 2.1
Name: customattack
Version: 1.4
Summary: A library for generating text adversarial examples
Home-page: https://github.com/QData/textattack
Author: QData Lab at the University of Virginia
Author-email: ujeong1@asu.edu
License: MIT
Platform: UNKNOWN
Classifier: Programming Language :: Python :: 3
Classifier: License :: OSI Approved :: MIT License
Classifier: Operating System :: OS Independent
Requires-Python: >=3.6
